ltr_lib/__init__.py
ltr_lib/cli.py
ltr_lib/core.py
ltr_lib/evaluation/__init__.py
ltr_lib/evaluation/metrics.py
ltr_lib/features/__init__.py
ltr_lib/features/engineering.py
ltr_lib/rankers/__init__.py
ltr_lib/rankers/base.py
ltr_lib/rankers/bm25.py
ltr_lib/rankers/lambdamart.py
ltr_lib/utils/__init__.py
ltr_lib-0.1.0.dist-info/METADATA
ltr_lib-0.1.0.dist-info/WHEEL
ltr_lib-0.1.0.dist-info/entry_points.txt
ltr_lib-0.1.0.dist-info/licenses/LICENSE
ltr_lib-0.1.0.dist-info/RECORD
