Metadata-Version: 2.4
Name: ltr-lib
Version: 0.1.0
Summary: A Learning-to-Rank library with LambdaMART, BM25, and MovieLens support
Project-URL: Homepage, https://github.com/AbhinaavRamesh/learning-to-rank-from-scratch
Project-URL: Repository, https://github.com/AbhinaavRamesh/learning-to-rank-from-scratch
Project-URL: Issues, https://github.com/AbhinaavRamesh/learning-to-rank-from-scratch/issues
Author: Abhinaav Ramesh
License: MIT
License-File: LICENSE
Keywords: bm25,information-retrieval,lambdamart,learning-to-rank,movielens,ndcg,ranking,recommendation
Classifier: Development Status :: 3 - Alpha
Classifier: Intended Audience :: Developers
Classifier: Intended Audience :: Science/Research
Classifier: License :: OSI Approved :: MIT License
Classifier: Operating System :: OS Independent
Classifier: Programming Language :: Python :: 3
Classifier: Programming Language :: Python :: 3.10
Classifier: Programming Language :: Python :: 3.11
Classifier: Programming Language :: Python :: 3.12
Classifier: Topic :: Scientific/Engineering :: Artificial Intelligence
Classifier: Topic :: Scientific/Engineering :: Information Analysis
Requires-Python: >=3.10
Requires-Dist: lightgbm>=4.0.0
Requires-Dist: numpy>=1.21.0
Requires-Dist: pandas>=1.3.0
Requires-Dist: rank-bm25>=0.2.2
Requires-Dist: scikit-learn>=1.0.0
Requires-Dist: scipy>=1.7.0
Provides-Extra: dev
Requires-Dist: mypy>=1.0.0; extra == 'dev'
Requires-Dist: pytest-cov>=4.0.0; extra == 'dev'
Requires-Dist: pytest>=7.0.0; extra == 'dev'
Requires-Dist: ruff>=0.1.0; extra == 'dev'
Provides-Extra: notebook
Requires-Dist: ipykernel>=6.0.0; extra == 'notebook'
Requires-Dist: jupyter>=1.0.0; extra == 'notebook'
Provides-Extra: viz
Requires-Dist: matplotlib>=3.4.0; extra == 'viz'
Requires-Dist: seaborn>=0.11.0; extra == 'viz'
